{
    "id": "33d9c61f658a4a08a7fb28a6484cd4cf",
    "customer_id": "77e9c4a0222d4c8cbd7a6830e1f7af42",
    "created_at": "2020-01-15T21:34:41.7253013Z",
    "text": "<p>amet aliquam erat euismod laoreet tincidunt laoreet nibh laoreet sed nibh sit dolore euismod consectetuer consectetuer. laoreet dolore laoreet aliquam adipiscing elit nonummy magna tincidunt nonummy euismod magna elit ipsum dolor ut. </p>",
    "ad_type": "Premium",
    "price": 17.08,
    "currency": "EUR",
    "payment_type": "Offline",
    "payment_cost": 0.0
}