{
    "id": "38d0d261fb28432ca3cf57f8191ee356",
    "customer_id": "235a1fa5d42744d599f5fea657309ef8",
    "created_at": "2020-01-15T21:47:41.5954105Z",
    "text": "<p>sed adipiscing lorem sed laoreet sit lorem sit nonummy magna sit tincidunt sit consectetuer diam lorem laoreet sed aliquam magna. amet sit euismod dolor amet ut ut erat amet nonummy ut laoreet dolore dolore adipiscing ut amet tincidunt dolor nonummy. </p>",
    "ad_type": "Platinum",
    "price": 31.5,
    "currency": "EUR",
    "payment_type": "Offline",
    "payment_cost": 0.0
}