{
    "id": "c60ecadc0aba4d00a0bc153a39b72388",
    "customer_id": "a17fea5ccb444d94804a667ea4e66f67",
    "created_at": "2020-01-15T22:12:41.7006833Z",
    "text": "<p>magna nibh erat erat aliquam euismod aliquam laoreet consectetuer ipsum nibh magna diam euismod sed. lorem dolor lorem nonummy sit euismod euismod nonummy amet nonummy diam adipiscing adipiscing dolore dolor. </p>",
    "ad_type": "Platinum",
    "price": 46.63,
    "currency": "EUR",
    "payment_type": "Card",
    "payment_cost": 0.47
}